[
  {
    "time": "00:00:30",
    "word": "말해줘요 언니",
    "ipa": "",
    "kk": "",
    "pos": "phrase",
    "zh": "請告訴我，姐姐",
    "en": "Please tell me, sister",
    "en_example": "말해줘요 언니, what should I do?",
    "zh_example": "請告訴我，姐姐，我該怎麼辦？",
    "ja": "말해줘요 언니",
    "local": "말해줘요 언니",
    "ko": "말해줘요 언니",
    "local_lang": "ko",
    "local_label": "韓文",
    "kana": "おしえてください、おねえさん",
    "local_pron": "malhaejwoyo eonni",
    "romaji": "oshiete kudasai, oneesan",
    "ja_example": "教えてください、お姉さん、どうすればいいですか？",
    "local_example": "教えてください、お姉さん、どうすればいいですか？",
    "ko_example": "教えてください、お姉さん、どうすればいいですか？",
    "ko_pron": "malhaejwoyo eonni"
  },
  {
    "time": "00:00:32",
    "word": "crying in my room",
    "ipa": "/ˈkraɪɪŋ ɪn maɪ rum/",
    "kk": "ˈkraɪɪŋ ɪn maɪ rum",
    "pos": "phrase",
    "zh": "在我的房間裡哭泣",
    "en": "She is crying in her room",
    "en_example": "I was crying in my room last night.",
    "zh_example": "我昨晚在房間裡哭泣。",
    "ja": "내 방에서 울고 있어요",
    "local": "내 방에서 울고 있어요",
    "ko": "내 방에서 울고 있어요",
    "local_lang": "ko",
    "local_label": "韓文",
    "kana": "わたしのへやでないている",
    "local_pron": "nae bangeseo ulgo isseoyo",
    "romaji": "watashi no heya de naite iru",
    "ja_example": "私は自分の部屋で泣いていました。",
    "local_example": "私は自分の部屋で泣いていました。",
    "ko_example": "私は自分の部屋で泣いていました。",
    "ko_pron": "nae bangeseo ulgo isseoyo"
  },
  {
    "time": "00:00:35",
    "word": "숨기고 싶어",
    "ipa": "",
    "kk": "",
    "pos": "phrase",
    "zh": "想要隱藏",
    "en": "I want to hide it",
    "en_example": "I want to hide my feelings.",
    "zh_example": "我想隱藏我的感情。",
    "ja": "숨기고 싶어",
    "local": "숨기고 싶어",
    "ko": "숨기고 싶어",
    "local_lang": "ko",
    "local_label": "韓文",
    "kana": "かくしたい",
    "local_pron": "sumgigo sipeo",
    "romaji": "kakushitai",
    "ja_example": "私はそれを隠したいです。",
    "local_example": "私はそれを隠したいです。",
    "ko_example": "私はそれを隠したいです。",
    "ko_pron": "sumgigo sipeo"
  },
  {
    "time": "00:00:38",
    "word": "But still I want it more, more, more",
    "ipa": "/bʌt stɪl aɪ wɑnt ɪt mɔr mɔr mɔr/",
    "kk": "bʌt stɪl aɪ wɑnt ɪt mɔr mɔr mɔr",
    "pos": "phrase",
    "zh": "但我仍然想要更多",
    "en": "However, I still desire it more and more",
    "en_example": "But still I want it more, more, more every day.",
    "zh_example": "但我每天仍然想要更多。",
    "ja": "하지만 나는 여전히 더 원해, 더, 더",
    "local": "하지만 나는 여전히 더 원해, 더, 더",
    "ko": "하지만 나는 여전히 더 원해, 더, 더",
    "local_lang": "ko",
    "local_label": "韓文",
    "kana": "でも、もっともっとほしい",
    "local_pron": "hajiman naneun yeojeonhi deo wonhae, deo, deo",
    "romaji": "demo, motto motto hoshii",
    "ja_example": "でも、私はもっともっと欲しいです。",
    "local_example": "でも、私はもっともっと欲しいです。",
    "ko_example": "でも、私はもっともっと欲しいです。",
    "ko_pron": "hajiman naneun yeojeonhi deo wonhae, deo, deo"
  },
  {
    "time": "00:00:41",
    "word": "I give a second chance to give back",
    "ipa": "/aɪ ɡɪv ə ˈsɛkənd ʧæns tə ɡɪv bæk/",
    "kk": "aɪ ɡɪv ə ˈsɛkənd ʧæns tə ɡɪv bæk",
    "pos": "phrase",
    "zh": "我給予第二次機會來回報",
    "en": "I offer a second chance to return something",
    "en_example": "I give a second chance to give back to those who helped me.",
    "zh_example": "我給予第二次機會來回報幫助過我的人。",
    "ja": "나는 돌려주기 위해 두 번째 기회를 준다",
    "local": "나는 돌려주기 위해 두 번째 기회를 준다",
    "ko": "나는 돌려주기 위해 두 번째 기회를 준다",
    "local_lang": "ko",
    "local_label": "韓文",
    "kana": "わたしはかえすためにもういちどチャンスをあたえる",
    "local_pron": "naneun dollyeojugi wihae du beonjjae gihoe reul junda",
    "romaji": "watashi wa kaesu tame ni mou ichido chansu o ataeru",
    "ja_example": "私は助けてくれた人に返すためにもう一度チャンスを与えます。",
    "local_example": "私は助けてくれた人に返すためにもう一度チャンスを与えます。",
    "ko_example": "私は助けてくれた人に返すためにもう一度チャンスを与えます。",
    "ko_pron": "naneun dollyeojugi wihae du beonjjae gihoe reul junda"
  },
  {
    "time": "00:00:45",
    "word": "날 믿은 내가 정말 stupid",
    "ipa": "",
    "kk": "",
    "pos": "phrase",
    "zh": "相信我的我真的很笨",
    "en": "I who trusted myself am really stupid",
    "en_example": "날 믿은 내가 정말 stupid, but I learned.",
    "zh_example": "相信我的我真的很笨，但我學到了。",
    "ja": "날 믿은 내가 정말 바보야",
    "local": "날 믿은 내가 정말 바보야",
    "ko": "날 믿은 내가 정말 바보야",
    "local_lang": "ko",
    "local_label": "韓文",
    "kana": "じぶんをしんじたわたしはほんとうにばかだ",
    "local_pron": "nal mideun naega jeongmal babo ya",
    "romaji": "jibun o shinjita watashi wa hontou ni baka da",
    "ja_example": "自分を信じた私は本当に馬鹿です。",
    "local_example": "自分を信じた私は本当に馬鹿です。",
    "ko_example": "自分を信じた私は本当に馬鹿です。",
    "ko_pron": "nal mideun naega jeongmal babo ya"
  },
  {
    "time": "00:00:50",
    "word": "보여줄게 숨겨",
    "ipa": "",
    "kk": "",
    "pos": "phrase",
    "zh": "我會展示，隱藏起來",
    "en": "I will show it, hide it",
    "en_example": "보여줄게 숨겨, just wait for me.",
    "zh_example": "我會展示，隱藏起來，等我。",
    "ja": "보여줄게 숨겨",
    "local": "보여줄게 숨겨",
    "ko": "보여줄게 숨겨",
    "local_lang": "ko",
    "local_label": "韓文",
    "kana": "みせるよ、かくして",
    "local_pron": "boyeojulge sumgyeo",
    "romaji": "miseru yo, kakushite",
    "ja_example": "見せるよ、隠してね。",
    "local_example": "見せるよ、隠してね。",
    "ko_example": "見せるよ、隠してね。",
    "ko_pron": "boyeojulge sumgyeo"
  },
  {
    "time": "00:00:52",
    "word": "But the love is in view",
    "ipa": "/bʌt ðə lʌv ɪz ɪn vju/",
    "kk": "bʌt ðə lʌv ɪz ɪn vju",
    "pos": "phrase",
    "zh": "但愛情在眼前",
    "en": "However, the love is visible",
    "en_example": "But the love is in view, don't hide it.",
    "zh_example": "但愛情就在眼前，不要隱藏它。",
    "ja": "하지만 사랑은 보인다",
    "local": "하지만 사랑은 보인다",
    "ko": "하지만 사랑은 보인다",
    "local_lang": "ko",
    "local_label": "韓文",
    "kana": "でもあいはみえている",
    "local_pron": "hajiman sarangeun boinda",
    "romaji": "demo ai wa miete iru",
    "ja_example": "でも愛は見えています。",
    "local_example": "でも愛は見えています。",
    "ko_example": "でも愛は見えています。",
    "ko_pron": "hajiman sarangeun boinda"
  },
  {
    "time": "00:00:55",
    "word": "You did it so done",
    "ipa": "/ju dɪd ɪt soʊ dʌn/",
    "kk": "ju dɪd ɪt soʊ dʌn",
    "pos": "phrase",
    "zh": "你已經完成了",
    "en": "You have completed it",
    "en_example": "You did it so done, congratulations!",
    "zh_example": "你已經完成了，恭喜！",
    "ja": "너는 그것을 끝냈어",
    "local": "너는 그것을 끝냈어",
    "ko": "너는 그것을 끝냈어",
    "local_lang": "ko",
    "local_label": "韓文",
    "kana": "あなたはそれをやりとげた",
    "local_pron": "neoneun geugeosul kkeunnaesseo",
    "romaji": "anata wa sore o yaritogeta",
    "ja_example": "あなたはそれをやり遂げました。",
    "local_example": "あなたはそれをやり遂げました。",
    "ko_example": "あなたはそれをやり遂げました。",
    "ko_pron": "neoneun geugeosul kkeunnaesseo"
  },
  {
    "time": "00:01:00",
    "word": "조금 길을 걷는 every day",
    "ipa": "",
    "kk": "",
    "pos": "phrase",
    "zh": "每天走一點路",
    "en": "Walking a little every day",
    "en_example": "I walk a little every day to stay healthy.",
    "zh_example": "我每天走一點路來保持健康。",
    "ja": "조금 길을 걷는 매일",
    "local": "조금 길을 걷는 매일",
    "ko": "조금 길을 걷는 매일",
    "local_lang": "ko",
    "local_label": "韓文",
    "kana": "まいにちすこしあるく",
    "local_pron": "jogeum gireul geodneun maeil",
    "romaji": "mainichi sukoshi aruku",
    "ja_example": "私は毎日少し歩きます。",
    "local_example": "私は毎日少し歩きます。",
    "ko_example": "私は毎日少し歩きます。",
    "ko_pron": "jogeum gireul geodneun maeil"
  },
  {
    "time": "00:01:04",
    "word": "넌 뜨면 다시 the fluid",
    "ipa": "",
    "kk": "",
    "pos": "phrase",
    "zh": "你一浮現就再次流動",
    "en": "You flow again when you rise",
    "en_example": "넌 뜨면 다시 the fluid, like water.",
    "zh_example": "你一浮現就像水一樣再次流動。",
    "ja": "넌 뜨면 다시 흐른다",
    "local": "넌 뜨면 다시 흐른다",
    "ko": "넌 뜨면 다시 흐른다",
    "local_lang": "ko",
    "local_label": "韓文",
    "kana": "あなたはうかぶとまたながれる",
    "local_pron": "neon tteumyeon dasi heureunda",
    "romaji": "anata wa ukabu to mata nagareru",
    "ja_example": "あなたは浮かぶとまた流れます。",
    "local_example": "あなたは浮かぶとまた流れます。",
    "ko_example": "あなたは浮かぶとまた流れます。",
    "ko_pron": "neon tteumyeon dasi heureunda"
  },
  {
    "time": "00:01:07",
    "word": "Waiting around is the way",
    "ipa": "/ˈweɪtɪŋ əˈraʊnd ɪz ðə weɪ/",
    "kk": "ˈweɪtɪŋ əˈraʊnd ɪz ðə weɪ",
    "pos": "phrase",
    "zh": "等待是方法",
    "en": "Waiting around is the method",
    "en_example": "Waiting around is the way to find answers.",
    "zh_example": "等待是找到答案的方法。",
    "ja": "기다리는 것이 방법이다",
    "local": "기다리는 것이 방법이다",
    "ko": "기다리는 것이 방법이다",
    "local_lang": "ko",
    "local_label": "韓文",
    "kana": "まつことがほうほうだ",
    "local_pron": "gidarineun geosi bangbeobida",
    "romaji": "matsu koto ga houhou da",
    "ja_example": "待つことが答えを見つける方法です。",
    "local_example": "待つことが答えを見つける方法です。",
    "ko_example": "待つことが答えを見つける方法です。",
    "ko_pron": "gidarineun geosi bangbeobida"
  },
  {
    "time": "00:01:09",
    "word": "나 솔직히 지금이 편해",
    "ipa": "",
    "kk": "",
    "pos": "phrase",
    "zh": "我坦白說現在很舒服",
    "en": "Honestly, I am comfortable now",
    "en_example": "나 솔직히 지금이 편해, no stress.",
    "zh_example": "我坦白說現在很舒服，沒有壓力。",
    "ja": "나 솔직히 지금이 편해",
    "local": "나 솔직히 지금이 편해",
    "ko": "나 솔직히 지금이 편해",
    "local_lang": "ko",
    "local_label": "韓文",
    "kana": "しょうじきにいうといまはらくだ",
    "local_pron": "na soljikhi jigeumi pyeonhae",
    "romaji": "shoujiki ni iu to ima wa raku da",
    "ja_example": "正直に言うと、今は楽です。",
    "local_example": "正直に言うと、今は楽です。",
    "ko_example": "正直に言うと、今は楽です。",
    "ko_pron": "na soljikhi jigeumi pyeonhae"
  },
  {
    "time": "00:01:11",
    "word": "상상만큼 잘 있단 걸까",
    "ipa": "",
    "kk": "",
    "pos": "phrase",
    "zh": "會像想像中那麼好嗎？",
    "en": "Is it as good as imagined?",
    "en_example": "상상만큼 잘 있단 걸까, I wonder.",
    "zh_example": "會像想像中那麼好嗎？我想知道。",
    "ja": "상상만큼 잘 있단 걸까",
    "local": "상상만큼 잘 있단 걸까",
    "ko": "상상만큼 잘 있단 걸까",
    "local_lang": "ko",
    "local_label": "韓文",
    "kana": "そうぞうしたほどうまくいっているのだろうか",
    "local_pron": "sangsangmankeum jal itdan geolkka",
    "romaji": "souzou shita hodo umaku itte iru no darou ka",
    "ja_example": "想像したほどうまくいっているのでしょうか？",
    "local_example": "想像したほどうまくいっているのでしょうか？",
    "ko_example": "想像したほどうまくいっているのでしょうか？",
    "ko_pron": "sangsangmankeum jal itdan geolkka"
  },
  {
    "time": "00:01:14",
    "word": "난 없어 언니",
    "ipa": "",
    "kk": "",
    "pos": "phrase",
    "zh": "我沒有，姐姐",
    "en": "I don't have it, sister",
    "en_example": "난 없어 언니, please help me.",
    "zh_example": "我沒有，姐姐，請幫幫我。",
    "ja": "난 없어 언니",
    "local": "난 없어 언니",
    "ko": "난 없어 언니",
    "local_lang": "ko",
    "local_label": "韓文",
    "kana": "わたしはもっていない、おねえさん",
    "local_pron": "nan eopseo eonni",
    "romaji": "watashi wa motte inai, oneesan",
    "ja_example": "私は持っていません、お姉さん。",
    "local_example": "私は持っていません、お姉さん。",
    "ko_example": "私は持っていません、お姉さん。",
    "ko_pron": "nan eopseo eonni"
  },
  {
    "time": "00:01:16",
    "word": "내 입속에서 연습했죠 it's me",
    "ipa": "",
    "kk": "",
    "pos": "phrase",
    "zh": "我在嘴裡練習了，是我",
    "en": "I practiced inside my mouth, it's me",
    "en_example": "내 입속에서 연습했죠 it's me, don't forget.",
    "zh_example": "我在嘴裡練習了，是我，別忘了。",
    "ja": "내 입속에서 연습했죠 it's me",
    "local": "내 입속에서 연습했죠 it's me",
    "ko": "내 입속에서 연습했죠 it's me",
    "local_lang": "ko",
    "local_label": "韓文",
    "kana": "くちのなかでれんしゅうしたよ、それはわたしだ",
    "local_pron": "nae ipsogeseo yeonseuphaetjyo its mi",
    "romaji": "kuchi no naka de renshuu shita yo, sore wa watashi da",
    "ja_example": "私は口の中で練習しました、それは私です。",
    "local_example": "私は口の中で練習しました、それは私です。",
    "ko_example": "私は口の中で練習しました、それは私です。",
    "ko_pron": "nae ipsogeseo yeonseuphaetjyo its mi"
  },
  {
    "time": "00:01:20",
    "word": "사실 crying in my room",
    "ipa": "",
    "kk": "",
    "pos": "phrase",
    "zh": "其實在我的房間裡哭泣",
    "en": "Actually crying in my room",
    "en_example": "사실 crying in my room, I feel sad.",
    "zh_example": "其實在我的房間裡哭泣，我感到難過。",
    "ja": "사실 내 방에서 울고 있어요",
    "local": "사실 내 방에서 울고 있어요",
    "ko": "사실 내 방에서 울고 있어요",
    "local_lang": "ko",
    "local_label": "韓文",
    "kana": "じつはわたしのへやでないている",
    "local_pron": "sasil nae bangeseo ulgo isseoyo",
    "romaji": "jitsu wa watashi no heya de naite iru",
    "ja_example": "実は私は自分の部屋で泣いています。",
    "local_example": "実は私は自分の部屋で泣いています。",
    "ko_example": "実は私は自分の部屋で泣いています。",
    "ko_pron": "sasil nae bangeseo ulgo isseoyo"
  },
  {
    "time": "00:01:23",
    "word": "포기할까봐",
    "ipa": "",
    "kk": "",
    "pos": "phrase",
    "zh": "害怕放棄",
    "en": "Afraid of giving up",
    "en_example": "포기할까봐, I keep trying.",
    "zh_example": "害怕放棄，我繼續努力。",
    "ja": "포기할까봐",
    "local": "포기할까봐",
    "ko": "포기할까봐",
    "local_lang": "ko",
    "local_label": "韓文",
    "kana": "あきらめるのがこわい",
    "local_pron": "pogihalkkabwa",
    "romaji": "akirameru no ga kowai",
    "ja_example": "諦めるのが怖いです。",
    "local_example": "諦めるのが怖いです。",
    "ko_example": "諦めるのが怖いです。",
    "ko_pron": "pogihalkkabwa"
  }
]