[
  {
    "type": "listening",
    "question": "What kind of shoes is the customer looking for?",
    "choices": [
      "Sneakers",
      "Leather shoes",
      "Sandals",
      "Running shoes"
    ],
    "answer": 1,
    "explanation": {
      "en": "The customer says, 'I'm looking for a pair of leather shoes.'",
      "zh": "顧客說：“我正在尋找一雙皮鞋。”",
      "ja": "お客様は「革靴を探しています」と言っています。"
    }
  },
  {
    "type": "listening",
    "question": "What size does the customer wear?",
    "choices": [
      "6",
      "7",
      "8",
      "9"
    ],
    "answer": 1,
    "explanation": {
      "en": "The customer answers '7' when asked about the shoe size.",
      "zh": "當被問到鞋碼時，顧客回答“7”。",
      "ja": "靴のサイズを聞かれて、お客様は「7」と答えています。"
    }
  },
  {
    "type": "listening",
    "question": "Why does the customer think buying the same brand is not a problem?",
    "choices": [
      "Because the price is lower",
      "Because the size is standard",
      "Because he wears size 7 in that brand",
      "Because the shoes are on sale"
    ],
    "answer": 2,
    "explanation": {
      "en": "The customer says he wears size 7 of Hush Puppies and wants to buy the same brand, so it shouldn't be a problem.",
      "zh": "顧客說他穿Hush Puppies的7號，想買同一品牌，所以不會有問題。",
      "ja": "お客様はハッシュパピーズの7サイズを履いていて、同じブランドを買いたいので問題ないと言っています。"
    }
  },
  {
    "type": "listening",
    "question": "What kind of shoes does the customer prefer?",
    "choices": [
      "Casual shoes",
      "Shoes on sale",
      "New arrivals",
      "Sports shoes"
    ],
    "answer": 2,
    "explanation": {
      "en": "The customer says, 'I'll prefer new arrivals.'",
      "zh": "顧客說：“我會選擇新品。”",
      "ja": "お客様は「新着商品を選びます」と言っています。"
    }
  },
  {
    "type": "listening",
    "question": "What kind of look is the customer looking for?",
    "choices": [
      "Casual look",
      "Sporty look",
      "Formal look",
      "Colorful look"
    ],
    "answer": 2,
    "explanation": {
      "en": "The customer says, 'I'm looking for more formal look, the ones with laces and predominantly plain texture.'",
      "zh": "顧客說：“我想要正式一點的款式，有鞋帶且主要是素色的。”",
      "ja": "お客様は「もっとフォーマルな見た目で、紐付きで主に無地のものを探しています」と言っています。"
    }
  },
  {
    "type": "vocab",
    "question": "What does 'new arrivals' mean in the context of the shoe store?",
    "choices": [
      "Shoes that are on sale",
      "Shoes that just came in stock",
      "Shoes that are out of stock",
      "Shoes that are used"
    ],
    "answer": 1,
    "explanation": {
      "en": "'New arrivals' refers to products that have recently arrived in the store.",
      "zh": "“新品”指的是最近到貨的商品。",
      "ja": "「新着商品」は最近入荷した商品を指します。"
    }
  },
  {
    "type": "vocab",
    "question": "What does 'billing' mean in the conversation?",
    "choices": [
      "Trying shoes on",
      "Paying for the purchase",
      "Returning shoes",
      "Asking for help"
    ],
    "answer": 1,
    "explanation": {
      "en": "'Billing' means the process of paying for the items purchased.",
      "zh": "“結帳”是指支付購買物品的過程。",
      "ja": "「請求」は購入した商品の支払い手続きを意味します。"
    }
  },
  {
    "type": "vocab",
    "question": "What does 'combo of three' refer to?",
    "choices": [
      "Three pairs of shoes",
      "Three pairs of socks sold together",
      "Three types of shoe polish",
      "Three brands of shoes"
    ],
    "answer": 1,
    "explanation": {
      "en": "'Combo of three' refers to selling three pairs of socks together as a set.",
      "zh": "“三件組合”指的是三雙襪子一起販售。",
      "ja": "「3個セット」は3足の靴下をまとめて販売することを指します。"
    }
  },
  {
    "type": "vocab",
    "question": "What does 'predominantly plain texture' mean?",
    "choices": [
      "Mostly colorful and patterned",
      "Mostly simple and without patterns",
      "Mostly shiny and glittery",
      "Mostly rough and uneven"
    ],
    "answer": 1,
    "explanation": {
      "en": "'Predominantly plain texture' means mostly simple and without patterns.",
      "zh": "“主要是素色的質地”指的是大部分是簡單且無花紋的。",
      "ja": "「主に無地の質感」は主にシンプルで模様がないことを意味します。"
    }
  },
  {
    "type": "vocab",
    "question": "What does 'fit well' mean in the context of trying shoes?",
    "choices": [
      "The shoe is too big",
      "The shoe is too small",
      "The shoe is comfortable and the right size",
      "The shoe is broken"
    ],
    "answer": 2,
    "explanation": {
      "en": "'Fit well' means the shoe is comfortable and the right size for the wearer.",
      "zh": "“合腳”指鞋子穿起來舒適且尺寸合適。",
      "ja": "「フィットする」は靴が快適でサイズが合っていることを意味します。"
    }
  },
  {
    "type": "grammar",
    "question": "Choose the correct sentence:",
    "choices": [
      "I wear signs to seven of hush puppies.",
      "I wear size seven of Hush Puppies.",
      "I wears size seven of Hush Puppies.",
      "I wearing size seven of Hush Puppies."
    ],
    "answer": 1,
    "explanation": {
      "en": "The correct sentence is 'I wear size seven of Hush Puppies.'",
      "zh": "正確句子是“我穿Hush Puppies的7號。”",
      "ja": "正しい文は「I wear size seven of Hush Puppies.」です。"
    }
  },
  {
    "type": "grammar",
    "question": "Which sentence is grammatically correct?",
    "choices": [
      "Does the same size mean different thing for different brands?",
      "Does the same size means different things for different brands?",
      "Does the same size mean different things for different brands?",
      "Do the same size mean different things for different brands?"
    ],
    "answer": 2,
    "explanation": {
      "en": "The correct sentence is 'Does the same size mean different things for different brands?'.",
      "zh": "正確句子是“不同品牌的同一尺寸是否意味著不同的東西？”",
      "ja": "正しい文は「Does the same size mean different things for different brands?」です。"
    }
  },
  {
    "type": "grammar",
    "question": "Choose the correct form: 'Most of the shoes on sale ___ picked up by customers within a day.'",
    "choices": [
      "was",
      "were",
      "is",
      "be"
    ],
    "answer": 1,
    "explanation": {
      "en": "'Shoes' is plural, so the correct verb is 'were'.",
      "zh": "“shoes”是複數，所以正確動詞是“were”。",
      "ja": "「shoes」は複数形なので、正しい動詞は「were」です。"
    }
  },
  {
    "type": "grammar",
    "question": "Which is correct?",
    "choices": [
      "I would like to buy something I like.",
      "I would like buy something I like.",
      "I would like buying something I like.",
      "I would like to buying something I like."
    ],
    "answer": 0,
    "explanation": {
      "en": "'Would like to buy' is the correct expression.",
      "zh": "“would like to buy”是正確用法。",
      "ja": "「would like to buy」が正しい表現です。"
    }
  },
  {
    "type": "grammar",
    "question": "Choose the correct question form:",
    "choices": [
      "Do you sell socks only in combo of three?",
      "Do you sell socks only in combos of three?",
      "Do you sell socks only in a combo of three?",
      "Do you sell socks only in combos of threes?"
    ],
    "answer": 2,
    "explanation": {
      "en": "The correct question is 'Do you sell socks only in a combo of three?'.",
      "zh": "正確問題是“Do you sell socks only in a combo of three?”",
      "ja": "正しい質問は「Do you sell socks only in a combo of three?」です。"
    }
  },
  {
    "type": "speaking",
    "question": "How would you ask for a formal pair of shoes with laces in a store?",
    "choices": [
      "I want casual shoes without laces.",
      "Do you have formal shoes with laces?",
      "Show me sandals please.",
      "I want colorful shoes."
    ],
    "answer": 1,
    "explanation": {
      "en": "The correct way is to ask, 'Do you have formal shoes with laces?'.",
      "zh": "正確說法是“你們有帶鞋帶的正式鞋嗎？”",
      "ja": "正しい言い方は「Do you have formal shoes with laces?」です。"
    }
  },
  {
    "type": "speaking",
    "question": "How do you say you want to try a shoe in English?",
    "choices": [
      "Let me try it.",
      "I will buy it now.",
      "I don't like it.",
      "Show me another one."
    ],
    "answer": 0,
    "explanation": {
      "en": "You say 'Let me try it.' to express wanting to try a shoe.",
      "zh": "想試穿鞋子時說“Let me try it.”",
      "ja": "靴を試したい時は「Let me try it.」と言います。"
    }
  },
  {
    "type": "speaking",
    "question": "How would you respond if a shop assistant asks, 'Would you like to see socks and shoe polish as well?'",
    "choices": [
      "No, thank you.",
      "Yes, I want socks.",
      "I don't like shoes.",
      "Show me sandals."
    ],
    "answer": 1,
    "explanation": {
      "en": "You can respond, 'Yes, I want socks.' if interested.",
      "zh": "如果有興趣，可以回答“是的，我要襪子。”",
      "ja": "興味があれば「Yes, I want socks.」と答えます。"
    }
  },
  {
    "type": "speaking",
    "question": "How do you say you want two pairs of socks in English?",
    "choices": [
      "I want two socks.",
      "I want two pairs of socks.",
      "I want two sock.",
      "I want two pair socks."
    ],
    "answer": 1,
    "explanation": {
      "en": "The correct phrase is 'two pairs of socks'.",
      "zh": "正確說法是“two pairs of socks”。",
      "ja": "正しい表現は「two pairs of socks」です。"
    }
  },
  {
    "type": "speaking",
    "question": "How would you ask for the price or to pay for your items in a store?",
    "choices": [
      "Can I get the billing done, please?",
      "I want to try shoes.",
      "Show me the new arrivals.",
      "Do you have this in size 8?"
    ],
    "answer": 0,
    "explanation": {
      "en": "You can say 'Can I get the billing done, please?' to ask to pay.",
      "zh": "你可以說“Can I get the billing done, please?”來請求結帳。",
      "ja": "「Can I get the billing done, please?」と言って支払いをお願いできます。"
    }
  }
]