[
  {
    "time": "00:00:10",
    "word": "passport",
    "pos": "noun",
    "zh": "護照",
    "en": "An official document issued by a government, certifying the holder's identity and citizenship.",
    "en_example": "May I see your passport please?",
    "zh_example": "請問我可以看一下你的護照嗎？",
    "ja": "パスポート",
    "ja_example": "パスポートを見せてください。"
  },
  {
    "time": "00:00:36",
    "word": "checking bags",
    "pos": "verb phrase",
    "zh": "托運行李",
    "en": "The process of handing over your luggage to the airline before a flight.",
    "en_example": "Are you checking any bags today?",
    "zh_example": "你今天有托運行李嗎？",
    "ja": "荷物を預ける",
    "ja_example": "今日は荷物を預けますか？"
  },
  {
    "time": "00:00:52",
    "word": "weight requirement",
    "pos": "noun phrase",
    "zh": "重量限制",
    "en": "The maximum allowed weight for luggage.",
    "en_example": "It is over our weight requirement.",
    "zh_example": "它超過了我們的重量限制。",
    "ja": "重量制限",
    "ja_example": "それは重量制限を超えています。"
  },
  {
    "time": "00:01:18",
    "word": "window seat",
    "pos": "noun phrase",
    "zh": "靠窗座位",
    "en": "A seat next to the window on an airplane.",
    "en_example": "I see you've chosen a window seat.",
    "zh_example": "我看到你選擇了靠窗座位。",
    "ja": "窓側の席",
    "ja_example": "窓側の席を選びましたね。"
  },
  {
    "time": "00:01:46",
    "word": "boarding pass",
    "pos": "noun",
    "zh": "登機證",
    "en": "A document that allows a passenger to enter the airplane.",
    "en_example": "Let me print your boarding pass.",
    "zh_example": "讓我幫你列印登機證。",
    "ja": "搭乗券",
    "ja_example": "搭乗券を印刷します。"
  },
  {
    "time": "00:02:03",
    "word": "departure",
    "pos": "noun",
    "zh": "出發",
    "en": "The act of leaving, especially to start a journey.",
    "en_example": "You should get to your gate about one hour before departure.",
    "zh_example": "你應該在出發前一小時到登機口。",
    "ja": "出発",
    "ja_example": "出発の1時間前にゲートに行ってください。"
  },
  {
    "time": "00:02:13",
    "word": "security",
    "pos": "noun",
    "zh": "安檢",
    "en": "The process of checking passengers and luggage for safety.",
    "en_example": "Security will be directly in front of you.",
    "zh_example": "安檢就在你前面。",
    "ja": "セキュリティチェック",
    "ja_example": "セキュリティはすぐ前にあります。"
  },
  {
    "time": "00:02:44",
    "word": "remove",
    "pos": "verb",
    "zh": "脫下，移除",
    "en": "To take something off or away.",
    "en_example": "You need to remove your coat and your belt.",
    "zh_example": "你需要脫下外套和皮帶。",
    "ja": "取り外す",
    "ja_example": "コートとベルトを取り外してください。"
  },
  {
    "time": "00:03:08",
    "word": "empty your pockets",
    "pos": "verb phrase",
    "zh": "清空口袋",
    "en": "To take everything out of your pockets.",
    "en_example": "You need to empty your pockets and put those items in the bin.",
    "zh_example": "你需要清空口袋並把物品放進箱子裡。",
    "ja": "ポケットの中身を出す",
    "ja_example": "ポケットの中身を出して箱に入れてください。"
  },
  {
    "time": "00:03:19",
    "word": "liquids",
    "pos": "noun",
    "zh": "液體",
    "en": "Substances that flow freely like water or juice.",
    "en_example": "Do you have any liquids in your bag?",
    "zh_example": "你的包裡有液體嗎？",
    "ja": "液体",
    "ja_example": "バッグの中に液体はありますか？"
  },
  {
    "time": "00:03:38",
    "word": "plastic bag",
    "pos": "noun phrase",
    "zh": "塑膠袋",
    "en": "A small bag made of plastic used to hold items.",
    "en_example": "You need to put it in a plastic bag.",
    "zh_example": "你需要把它放進塑膠袋裡。",
    "ja": "ビニール袋",
    "ja_example": "それをビニール袋に入れてください。"
  },
  {
    "time": "00:04:10",
    "word": "conveyor belt",
    "pos": "noun phrase",
    "zh": "輸送帶",
    "en": "A moving belt that carries luggage through security.",
    "en_example": "Please put your bag on the conveyor belt.",
    "zh_example": "請把你的包放在輸送帶上。",
    "ja": "コンベヤーベルト",
    "ja_example": "バッグをコンベヤーベルトに置いてください。"
  },
  {
    "time": "00:04:30",
    "word": "scan",
    "pos": "verb",
    "zh": "掃描",
    "en": "To examine something carefully with a machine.",
    "en_example": "I'm going to scan your body.",
    "zh_example": "我要掃描你的身體。",
    "ja": "スキャンする",
    "ja_example": "体をスキャンします。"
  },
  {
    "time": "00:04:37",
    "word": "trigger the alarm",
    "pos": "verb phrase",
    "zh": "觸發警報",
    "en": "To cause the security alarm to sound.",
    "en_example": "I think my necklace triggered the alarm.",
    "zh_example": "我想我的項鍊觸發了警報。",
    "ja": "アラームを鳴らす",
    "ja_example": "ネックレスがアラームを鳴らしたと思います。"
  },
  {
    "time": "00:05:01",
    "word": "boarding",
    "pos": "verb",
    "zh": "登機",
    "en": "The process of getting on an airplane.",
    "en_example": "Flight 803 to London is now boarding.",
    "zh_example": "飛往倫敦的803航班正在登機。",
    "ja": "搭乗",
    "ja_example": "ロンドン行きの803便は搭乗中です。"
  },
  {
    "time": "00:06:04",
    "word": "serve",
    "pos": "verb",
    "zh": "供應（食物或飲料）",
    "en": "To provide food or drinks to someone.",
    "en_example": "We serve coffee, tea, and soda.",
    "zh_example": "我們供應咖啡、茶和汽水。",
    "ja": "提供する",
    "ja_example": "コーヒー、紅茶、ソーダを提供しています。"
  },
  {
    "time": "00:06:24",
    "word": "turkey sandwich",
    "pos": "noun phrase",
    "zh": "火雞三明治",
    "en": "A sandwich made with turkey meat.",
    "en_example": "I think I'll have the turkey sandwich.",
    "zh_example": "我想我要火雞三明治。",
    "ja": "ターキーサンドイッチ",
    "ja_example": "ターキーサンドイッチにします。"
  },
  {
    "time": "00:07:02",
    "word": "carousel",
    "pos": "noun",
    "zh": "行李轉盤",
    "en": "A rotating conveyor belt where passengers pick up their luggage.",
    "en_example": "Your bag will be arriving on Carousel 4.",
    "zh_example": "你的行李會在4號行李轉盤出現。",
    "ja": "手荷物受取所の回転台",
    "ja_example": "荷物は4番の回転台に届きます。"
  },
  {
    "time": "00:07:32",
    "word": "declare",
    "pos": "verb",
    "zh": "申報",
    "en": "To officially state something, especially at customs.",
    "en_example": "Do you have anything to declare?",
    "zh_example": "你有什麼需要申報的嗎？",
    "ja": "申告する",
    "ja_example": "申告するものはありますか？"
  },
  {
    "time": "00:07:35",
    "word": "purpose of your visit",
    "pos": "noun phrase",
    "zh": "訪問目的",
    "en": "The reason why someone is visiting a place.",
    "en_example": "What is the purpose of your visit?",
    "zh_example": "你的訪問目的為何？",
    "ja": "訪問の目的",
    "ja_example": "訪問の目的は何ですか？"
  }
]