[
  {
    "time": "00:00:00",
    "word": "recycling",
    "pos": "verb",
    "zh": "回收利用",
    "en": "Recycling helps reduce waste and protect the environment.",
    "en_example": "Recycling helps reduce waste and protect the environment.",
    "zh_example": "Recycling helps reduce waste and protect the environment.",
    "ja": "リサイクル",
    "ja_example": "Recycling helps reduce waste and protect the environment."
  },
  {
    "time": "00:00:11",
    "word": "landfill",
    "pos": "noun",
    "zh": "垃圾掩埋場",
    "en": "Many trash items end up in a landfill.",
    "en_example": "Many trash items end up in a landfill.",
    "zh_example": "Many trash items end up in a landfill.",
    "ja": "埋立地",
    "ja_example": "Many trash items end up in a landfill."
  },
  {
    "time": "00:00:17",
    "word": "waste",
    "pos": "noun",
    "zh": "廢棄物",
    "en": "We should reduce waste to help the planet.",
    "en_example": "We should reduce waste to help the planet.",
    "zh_example": "We should reduce waste to help the planet.",
    "ja": "廃棄物",
    "ja_example": "We should reduce waste to help the planet."
  },
  {
    "time": "00:00:05",
    "word": "environment",
    "pos": "noun",
    "zh": "環境",
    "en": "Protecting the environment is important for future generations.",
    "en_example": "Protecting the environment is important for future generations.",
    "zh_example": "Protecting the environment is important for future generations.",
    "ja": "環境",
    "ja_example": "Protecting the environment is important for future generations."
  },
  {
    "time": "00:00:28",
    "word": "sort",
    "pos": "noun",
    "zh": "分類",
    "en": "Please sort your recycling into different bins.",
    "en_example": "Please sort your recycling into different bins.",
    "zh_example": "Please sort your recycling into different bins.",
    "ja": "分別する",
    "ja_example": "Please sort your recycling into different bins."
  },
  {
    "time": "00:00:32",
    "word": "reduce",
    "pos": "noun",
    "zh": "減少",
    "en": "We need to reduce the amount of plastic we use.",
    "en_example": "We need to reduce the amount of plastic we use.",
    "zh_example": "We need to reduce the amount of plastic we use.",
    "ja": "減らす",
    "ja_example": "We need to reduce the amount of plastic we use."
  },
  {
    "time": "00:00:32",
    "word": "natural resources",
    "pos": "phrase",
    "zh": "自然資源",
    "en": "Recycling saves natural resources like water and trees.",
    "en_example": "Recycling saves natural resources like water and trees.",
    "zh_example": "Recycling saves natural resources like water and trees.",
    "ja": "天然資源",
    "ja_example": "Recycling saves natural resources like water and trees."
  },
  {
    "time": "00:00:39",
    "word": "plastic",
    "pos": "noun",
    "zh": "塑膠",
    "en": "Plastic can be recycled into new products.",
    "en_example": "Plastic can be recycled into new products.",
    "zh_example": "Plastic can be recycled into new products.",
    "ja": "プラスチック",
    "ja_example": "Plastic can be recycled into new products."
  },
  {
    "time": "00:00:39",
    "word": "paper",
    "pos": "noun",
    "zh": "紙張",
    "en": "Paper is one of the materials we can recycle.",
    "en_example": "Paper is one of the materials we can recycle.",
    "zh_example": "Paper is one of the materials we can recycle.",
    "ja": "紙",
    "ja_example": "Paper is one of the materials we can recycle."
  },
  {
    "time": "00:00:39",
    "word": "glass",
    "pos": "noun",
    "zh": "玻璃",
    "en": "Glass bottles should be placed in the glass recycling bin.",
    "en_example": "Glass bottles should be placed in the glass recycling bin.",
    "zh_example": "Glass bottles should be placed in the glass recycling bin.",
    "ja": "ガラス",
    "ja_example": "Glass bottles should be placed in the glass recycling bin."
  },
  {
    "time": "00:00:53",
    "word": "ecosystem",
    "pos": "noun",
    "zh": "生態系統",
    "en": "Recycling helps keep our ecosystem healthy.",
    "en_example": "Recycling helps keep our ecosystem healthy.",
    "zh_example": "Recycling helps keep our ecosystem healthy.",
    "ja": "生態系",
    "ja_example": "Recycling helps keep our ecosystem healthy."
  },
  {
    "time": "00:00:53",
    "word": "emissions",
    "pos": "noun",
    "zh": "排放物",
    "en": "Reducing emissions helps fight climate change.",
    "en_example": "Reducing emissions helps fight climate change.",
    "zh_example": "Reducing emissions helps fight climate change.",
    "ja": "排出物",
    "ja_example": "Reducing emissions helps fight climate change."
  },
  {
    "time": "00:00:53",
    "word": "energy",
    "pos": "noun",
    "zh": "能源",
    "en": "Recycling saves energy compared to making new products.",
    "en_example": "Recycling saves energy compared to making new products.",
    "zh_example": "Recycling saves energy compared to making new products.",
    "ja": "エネルギー",
    "ja_example": "Recycling saves energy compared to making new products."
  },
  {
    "time": "00:00:00",
    "word": "create jobs",
    "pos": "phrase",
    "zh": "創造就業機會",
    "en": "Recycling programs create jobs in the community.",
    "en_example": "Recycling programs create jobs in the community.",
    "zh_example": "Recycling programs create jobs in the community.",
    "ja": "雇用を創出する",
    "ja_example": "Recycling programs create jobs in the community."
  },
  {
    "time": "00:01:02",
    "word": "small actions",
    "pos": "phrase",
    "zh": "小行動",
    "en": "Small actions like recycling can make a big difference.",
    "en_example": "Small actions like recycling can make a big difference.",
    "zh_example": "Small actions like recycling can make a big difference.",
    "ja": "小さな行動",
    "ja_example": "Small actions like recycling can make a big difference."
  }
]