[
  {
    "time": "00:00:00",
    "word": "shopkeeper",
    "pos": "noun",
    "zh": "店主，商店老闆",
    "en": "A person who owns or manages a small shop or store.",
    "en_example": "This is Arthur. He is a shopkeeper.",
    "zh_example": "這是亞瑟。他是一位店主。",
    "ja": "店主、商店の経営者",
    "ja_example": "こちらはアーサーです。彼は店主です。"
  },
  {
    "time": "00:00:40",
    "word": "function",
    "pos": "noun",
    "zh": "社交活動，聚會",
    "en": "A social event or gathering.",
    "en_example": "Dad, I need money. I have a function tonight.",
    "zh_example": "爸爸，我需要錢。我今晚有個活動。",
    "ja": "イベント、社交の集まり",
    "ja_example": "お父さん、お金が必要だ。今夜イベントがあるんだ。"
  },
  {
    "time": "00:00:24",
    "word": "bills",
    "pos": "noun",
    "zh": "帳單，費用",
    "en": "Statements of money owed for goods or services.",
    "en_example": "Good, Arthur. But we need to sell more. Bills are big this month.",
    "zh_example": "很好，亞瑟。但我們需要賣更多。這個月帳單很大。",
    "ja": "請求書、支払い",
    "ja_example": "いいわね、アーサー。でももっと売らなきゃ。今月の請求書が大きいの。"
  },
  {
    "time": "00:01:01",
    "word": "figure it out",
    "pos": "phrase",
    "zh": "想出解決方法，弄清楚",
    "en": "To find a solution or understand something.",
    "en_example": "You will figure it out, Dad. You always do.",
    "zh_example": "你會想辦法的，爸爸。你總是能做到。",
    "ja": "解決策を見つける、理解する",
    "ja_example": "お父さん、あなたなら何とかするよ。いつもそうだろ。"
  },
  {
    "time": "00:01:42",
    "word": "upset",
    "pos": "adjective",
    "zh": "心煩意亂，難過",
    "en": "Feeling unhappy or worried.",
    "en_example": "What is wrong, Charles? You seem upset.",
    "zh_example": "怎麼了，查爾斯？你看起來不高興。",
    "ja": "動揺している、悲しい",
    "ja_example": "どうしたんだ、チャールズ？怒っているように見えるよ。"
  },
  {
    "time": "00:02:05",
    "word": "grown up",
    "pos": "adjective",
    "zh": "長大成人",
    "en": "Having reached adulthood or maturity.",
    "en_example": "Dad, we are grown up now. We have dreams.",
    "zh_example": "爸爸，我們已經長大了。我們有夢想。",
    "ja": "大人になった",
    "ja_example": "お父さん、僕たちはもう大人だ。夢があるんだ。"
  },
  {
    "time": "00:03:56",
    "word": "bread and butter",
    "pos": "phrase",
    "zh": "生計，主要收入來源",
    "en": "The main source of income or livelihood.",
    "en_example": "This shop is my life. It is our bread and butter.",
    "zh_example": "這家店是我的生命。是我們的生計。",
    "ja": "生活の糧、主な収入源",
    "ja_example": "この店は俺の人生だ。俺たちの生活の糧だ。"
  },
  {
    "time": "00:03:02",
    "word": "give up",
    "pos": "verb",
    "zh": "放棄",
    "en": "To stop trying or surrender.",
    "en_example": "You are strong, Arthur. Do not give up.",
    "zh_example": "你很堅強，亞瑟。不要放棄。",
    "ja": "諦める",
    "ja_example": "アーサー、君は強い。諦めるな。"
  },
  {
    "time": "00:03:17",
    "word": "deliveries",
    "pos": "noun",
    "zh": "送貨，配送",
    "en": "The act of bringing goods to a destination.",
    "en_example": "Yes, I will deliver the stuff. Don't worry.",
    "zh_example": "是的，我會送貨。別擔心。",
    "ja": "配達",
    "ja_example": "はい、荷物を配達します。心配しないで。"
  },
  {
    "time": "00:04:02",
    "word": "invest",
    "pos": "verb",
    "zh": "投資",
    "en": "To put money into something to gain profit or advantage.",
    "en_example": "Because it is small. What will you do with it? We can get good money and invest in something big.",
    "zh_example": "因為它太小了。你打算怎麼辦？我們可以賣個好價錢，投資更大的事業。",
    "ja": "投資する",
    "ja_example": "小さいからだ。どうするんだ？いいお金になるし、大きなことに投資できる。"
  },
  {
    "time": "00:05:06",
    "word": "appreciate",
    "pos": "verb",
    "zh": "感激，欣賞",
    "en": "To recognize the value or importance of something or someone.",
    "en_example": "When they will realize your hard work, they will appreciate you and they will value the shop.",
    "zh_example": "當他們意識到你的努力時，他們會感激你，也會珍惜這家店。",
    "ja": "感謝する、評価する",
    "ja_example": "君の努力に気づいた時、彼らは感謝し、この店を大切にするだろう。"
  },
  {
    "time": "00:05:27",
    "word": "close",
    "pos": "adjective",
    "zh": "親近的，關係密切的",
    "en": "Having a strong personal relationship or feeling near to someone.",
    "en_example": "Boys, I want to talk. I feel we are not close anymore.",
    "zh_example": "孩子們，我想談談。我覺得我們不再親近了。",
    "ja": "親しい、近い",
    "ja_example": "みんな、話がある。もう親しくない気がする。"
  },
  {
    "time": "00:06:03",
    "word": "clothed",
    "pos": "verb",
    "zh": "穿衣，提供衣物",
    "en": "To provide or cover with clothes.",
    "en_example": "It is everything. This shop fed you, clothed you, educated you.",
    "zh_example": "它就是一切。這家店養活你，給你衣服，供你讀書。",
    "ja": "服を着せる",
    "ja_example": "それが全てだ。この店が君を養い、服を与え、教育した。"
  },
  {
    "time": "00:10:55",
    "word": "dignity",
    "pos": "noun",
    "zh": "尊嚴",
    "en": "The state or quality of being worthy of honor or respect.",
    "en_example": "I refuse to sell my dignity. If you think this shop is a burden, you are free to leave.",
    "zh_example": "我拒絕賣掉我的尊嚴。如果你認為這家店是負擔，你可以離開。",
    "ja": "尊厳",
    "ja_example": "俺は誇りを売らない。店が重荷だと思うなら、出て行っていい。"
  },
  {
    "time": "00:11:29",
    "word": "earn money",
    "pos": "phrase",
    "zh": "賺錢",
    "en": "To receive money in return for work or services.",
    "en_example": "Earned money to understand its value.",
    "zh_example": "賺錢才能懂得它的價值。",
    "ja": "お金を稼ぐ",
    "ja_example": "お金を稼いでその価値を理解しろ。"
  },
  {
    "time": "00:16:03",
    "word": "deliveries",
    "pos": "noun",
    "zh": "送貨，配送",
    "en": "The act of transporting goods to a recipient.",
    "en_example": "I found a way to make good money, Mom. I am doing deliveries for Tom. It pays well.",
    "zh_example": "媽媽，我找到賺錢的方法。我在幫湯姆送貨。報酬不錯。",
    "ja": "配達",
    "ja_example": "お母さん、いい稼ぎ方を見つけた。トムの配達をしている。給料はいい。"
  },
  {
    "time": "00:14:37",
    "word": "legal",
    "pos": "adjective",
    "zh": "合法的",
    "en": "Allowed by law; lawful.",
    "en_example": "Is it legal, Tom? Legal or not, it's money, Charles. You want to make it big or not.",
    "zh_example": "這合法嗎，湯姆？合法不合法，這是錢，查爾斯。你想成功還是不想？",
    "ja": "合法の",
    "ja_example": "合法か、トム？合法かどうかは関係ない、金だ、チャールズ。成功したいか？"
  },
  {
    "time": "00:13:06",
    "word": "engaged",
    "pos": "adjective",
    "zh": "訂婚的",
    "en": "Having formally agreed to marry.",
    "en_example": "I will ask her. Once Gina and I are engaged, I will take care of her father's business.",
    "zh_example": "我會問她。一旦吉娜和我訂婚，我會照顧她父親的生意。",
    "ja": "婚約している",
    "ja_example": "彼女に頼む。ジーナと婚約したら、彼女の父親のビジネスを引き継ぐ。"
  },
  {
    "time": "00:18:03",
    "word": "cafe",
    "pos": "noun",
    "zh": "咖啡館",
    "en": "A small restaurant where coffee and light meals are served.",
    "en_example": "What if you turn part of your shop into a cafe? A place where people can relax?",
    "zh_example": "如果你把店的一部分改成咖啡館呢？一個讓人放鬆的地方？",
    "ja": "カフェ",
    "ja_example": "店の一部をカフェにしたらどうだ？人々がくつろげる場所だ。"
  },
  {
    "time": "00:20:18",
    "word": "cheated",
    "pos": "verb",
    "zh": "欺騙，作弊",
    "en": "To act dishonestly or unfairly to gain an advantage.",
    "en_example": "You have cheated me. Even I don't drive a twelve million car.",
    "zh_example": "你欺騙了我。連我都沒開過1200萬的車。",
    "ja": "騙した",
    "ja_example": "俺を騙したな。俺でさえ1200万の車は運転していない。"
  },
  {
    "time": "00:21:10",
    "word": "arrested",
    "pos": "verb",
    "zh": "被逮捕",
    "en": "To be taken into custody by the police.",
    "en_example": "What happened Charles? Why have they arrested you?",
    "zh_example": "發生什麼事了，查爾斯？他們為什麼逮捕你？",
    "ja": "逮捕された",
    "ja_example": "何があった、チャールズ？なぜ逮捕された？"
  },
  {
    "time": "00:21:28",
    "word": "bail",
    "pos": "noun",
    "zh": "保釋金",
    "en": "Money paid to release someone from jail until trial.",
    "en_example": "You can bail him out. The bail amount is ten thousand dollars.",
    "zh_example": "你可以保釋他。保釋金是一萬美元。",
    "ja": "保釈金",
    "ja_example": "保釈できる。保釈金は1万ドルだ。"
  },
  {
    "time": "00:23:18",
    "word": "perfume",
    "pos": "noun",
    "zh": "香水",
    "en": "A fragrant liquid typically used to give a pleasant smell to the body.",
    "en_example": "It was ladies perfume for men.",
    "zh_example": "是男用女士香水。",
    "ja": "香水",
    "ja_example": "男性用の女性香水だった。"
  }
]