[
  {
    "time": "00:00:00",
    "en": "Thank you so much for watching, and I'll see you in the next video, and I'll see you in the next video, and I'll see you in the next video.",
    "zh": "非常感謝你的觀看，我們下個影片見，下個影片見，下個影片見。",
    "ja": "ご視聴ありがとうございました。次の動画でお会いしましょう、次の動画でお会いしましょう、次の動画でお会いしましょう。",
    "source_url": "https://www.youtube.com/watch?v=vEMId4GUEVQ"
  },
  {
    "time": "00:00:30",
    "en": "Hi, Bradley.",
    "zh": "嗨，布拉德利。",
    "ja": "こんにちは、ブラッドリー。"
  },
  {
    "time": "00:00:54",
    "en": "More than I be.",
    "zh": "比我還多。",
    "ja": "私より多いよ。"
  },
  {
    "time": "00:00:55",
    "en": "Okay, good. You're here early. I put this on her knee.",
    "zh": "好的，太好了。你來得早。我把這個放在她膝蓋上。",
    "ja": "はい、いいですね。早く来ましたね。これを彼女の膝に置きました。"
  },
  {
    "time": "00:01:02",
    "en": "Okay. What's up with you? You forgot? I can't believe you. Today is the...",
    "zh": "好吧。你怎麼了？你忘了？我不敢相信你。今天是...",
    "ja": "はい。どうしたの？忘れたの？信じられないよ。今日は..."
  },
  {
    "time": "00:01:10",
    "en": "You remembered. They got you.",
    "zh": "你記得了。他們抓到你了。",
    "ja": "覚えてたね。彼らに捕まったよ。"
  },
  {
    "time": "00:01:13",
    "en": "Okay, so I need everything as clean as possible for Mr. Donnelly's arrival, or do we just leave everything dishevel?",
    "zh": "好，那我需要把一切整理得盡可能乾淨，等唐納利先生來，還是我們就讓一切凌亂不堪？",
    "ja": "では、ドネリーさんの到着に向けてできるだけ綺麗にしておくべきですか？それとも全部散らかしたままにしますか？"
  },
  {
    "time": "00:01:20",
    "en": "So he realizes how much we need his donation? What do you think?",
    "zh": "這樣他就會知道我們多需要他的捐款？你覺得呢？",
    "ja": "そうすれば彼は私たちがどれだけ寄付を必要としているか気づく？どう思う？"
  },
  {
    "time": "00:01:23",
    "en": "I think it's going to be fine no matter what.",
    "zh": "我覺得不管怎樣都會沒問題的。",
    "ja": "何があっても大丈夫だと思うよ。"
  },
  {
    "time": "00:01:27",
    "en": "Okay. Who's first, Bradley?",
    "zh": "好。誰先來，布拉德利？",
    "ja": "はい。誰が最初？ブラッドリー？"
  },
  {
    "time": "00:01:36",
    "en": "How much longer? Any minute, I think. I should have just had you go in my place.",
    "zh": "還要多久？我想隨時會來。我本該讓你代替我去的。",
    "ja": "あとどれくらい？もうすぐだと思う。君に代わりに行ってもらえばよかった。"
  },
  {
    "time": "00:01:42",
    "en": "People want to meet you, Dylan, not me. We'll be quick.",
    "zh": "大家想見的是你，迪倫，不是我。我們會很快的。",
    "ja": "みんなが会いたいのは君だ、ディラン、僕じゃない。すぐ終わるよ。"
  },
  {
    "time": "00:01:46",
    "en": "Just a few photos and a video to show what a bleeding heart you are.",
    "zh": "只是幾張照片和一段影片，展示你多麼有愛心。",
    "ja": "ほんの数枚の写真とビデオで、君の情熱を見せるだけだ。"
  },
  {
    "time": "00:01:50",
    "en": "Anyone with half a brain can look up how much I donate to charities.",
    "zh": "有點腦子的人都能查到我捐了多少給慈善機構。",
    "ja": "少しでも頭があれば、僕がどれだけ寄付しているか調べられる。"
  },
  {
    "time": "00:01:54",
    "en": "Yes, but let's make it easier. No one wants to look up information these days.",
    "zh": "是啊，但我們讓事情更簡單點。現在沒人想去查資料。",
    "ja": "そうだけど、もっと簡単にしよう。今は誰も情報を調べたくない。"
  },
  {
    "time": "00:01:58",
    "en": "They want to be spoon-fed, so let's spoon-feed them some good PR.",
    "zh": "他們想被餵食，所以我們就餵他們一些好的公關。",
    "ja": "みんなスプーンで食べさせてもらいたいんだ。だからいいPRを与えよう。"
  },
  {
    "time": "00:02:04",
    "en": "If it makes people forget the rumors that are tanking my stock, then buy all means.",
    "zh": "如果這能讓人忘記那些讓我股價暴跌的謠言，那就盡管做吧。",
    "ja": "もしそれで株価を下げる噂を忘れさせられるなら、ぜひやろう。"
  },
  {
    "time": "00:02:09",
    "en": "Let's write up your head, sir.",
    "zh": "讓我們寫寫你的頭像，先生。",
    "ja": "あなたの肖像を書きましょう、先生。"
  },
  {
    "time": "00:02:14",
    "en": "This is it.",
    "zh": "就是這裡。",
    "ja": "ここだ。"
  },
  {
    "time": "00:02:16",
    "en": "What did you expect? Something with a sidewalk, and a parking lot.",
    "zh": "你期待什麼？有行人道和停車場的地方嗎？",
    "ja": "何を期待してた？歩道や駐車場がある場所？"
  },
  {
    "time": "00:02:21",
    "en": "Well, here he comes. Okay. Do you have your camera?",
    "zh": "他來了。好。你帶相機了嗎？",
    "ja": "ほら、彼が来たよ。カメラは持ってる？"
  },
  {
    "time": "00:02:26",
    "en": "Yes. Okay, great. Thank you, Ivy. Hang on, I'm with a patient.",
    "zh": "有。好，太好了。謝謝你，艾薇。等一下，我正在看病人。",
    "ja": "はい。いいね。ありがとう、アイビー。ちょっと待って、患者さんと一緒だ。"
  },
  {
    "time": "00:02:31",
    "en": "Hello, and welcome to the Tinang Valley Health Clinic, Mr. Donnelly.",
    "zh": "您好，歡迎來到蒂南谷健康診所，唐納利先生。",
    "ja": "こんにちは、ティナングバレー健康クリニックへようこそ、ドネリーさん。"
  },
  {
    "time": "00:02:36",
    "en": "Is this all of it? Yes, it's small, but we're only one of five clinics throughout the island.",
    "zh": "這就是全部嗎？是的，雖然小，但我們是島上五家診所之一。",
    "ja": "これが全部ですか？はい、小さいですが島内に5つあるクリニックの一つです。"
  },
  {
    "time": "00:02:43",
    "en": "Blake Vance, you must be Jocelyn. Hi.",
    "zh": "布雷克·范斯，你一定是喬斯林。你好。",
    "ja": "ブレイク・ヴァンス、あなたがジョスリンですね。こんにちは。"
  },
  {
    "time": "00:02:46",
    "en": "What a nice clinic you have here. Thank you.",
    "zh": "你們這裡的診所真不錯。謝謝。",
    "ja": "素敵なクリニックですね。ありがとうございます。"
  },
  {
    "time": "00:02:49",
    "en": "Your first donation, it comes at a critical time for our clinics.",
    "zh": "你的首次捐款，對我們診所來說正是關鍵時刻。",
    "ja": "あなたの最初の寄付は、私たちのクリニックにとって重要な時期に来ました。"
  },
  {
    "time": "00:02:53",
    "en": "We service more rural villages.",
    "zh": "我們服務更多偏遠村莊。",
    "ja": "私たちはより多くの田舎の村々にサービスを提供しています。"
  },
  {
    "time": "00:02:57",
    "en": "People who can't afford health services and government run hospitals.",
    "zh": "那些負擔不起醫療服務和政府醫院的人們。",
    "ja": "医療サービスや政府運営の病院を利用できない人々です。"
  },
  {
    "time": "00:03:03",
    "en": "I understand you intend to get more staff and supplies with the pun.",
    "zh": "我知道你打算用這筆資金增加人手和物資。",
    "ja": "この資金でスタッフと物資を増やすつもりだと聞いています。"
  },
  {
    "time": "00:03:07",
    "en": "Yes, myself and two other doctors are here at this clinic, and at the other clinic we have.",
    "zh": "是的，我和另外兩位醫生在這家診所，還有另一家診所。",
    "ja": "はい、私と他の2人の医師がこのクリニックにいて、もう一つのクリニックにもいます。"
  },
  {
    "time": "00:03:12",
    "en": "Blake, you're with us long. Okay.",
    "zh": "布雷克，你跟我們多久了？好。",
    "ja": "ブレイク、長く一緒にいるね。はい。"
  },
  {
    "time": "00:03:15",
    "en": "Let's take some photos and meet the team.",
    "zh": "我們拍些照片，認識團隊吧。",
    "ja": "写真を撮ってチームに会いましょう。"
  },
  {
    "time": "00:03:18",
    "en": "Okay, follow me.",
    "zh": "好，跟我來。",
    "ja": "はい、ついてきて。"
  },
  {
    "time": "00:03:21",
    "en": "So here we have Dr. Ivy Miller.",
    "zh": "這是艾薇·米勒醫生。",
    "ja": "こちらがアイビー・ミラー医師です。"
  },
  {
    "time": "00:03:24",
    "en": "She is so dedicated.",
    "zh": "她非常敬業。",
    "ja": "彼女はとても献身的です。"
  },
  {
    "time": "00:03:26",
    "en": "I'm willing to lead to the last patient to see.",
    "zh": "我願意帶領直到最後一位病人。",
    "ja": "最後の患者を見るまで付き合う覚悟です。"
  },
  {
    "time": "00:03:28",
    "en": "Our other doctor, Dr. Wresh, rotates and shifts, and should be here tomorrow.",
    "zh": "我們另一位醫生沃雷什輪班，明天應該會來。",
    "ja": "もう一人の医師、ウォレッシュ医師は交代勤務で、明日来る予定です。"
  },
  {
    "time": "00:03:32",
    "en": "I'm almost done. Well, maybe we could get some shots with you working here.",
    "zh": "我快完成了。也許我們可以拍一些你在這裡工作的照片。",
    "ja": "もうすぐ終わります。ここで働いている写真を撮りましょうか。"
  },
  {
    "time": "00:03:36",
    "en": "Oh, okay. Just need to make sure it's okay with her.",
    "zh": "喔，好。只是要確定她沒問題。",
    "ja": "ああ、わかった。彼女の許可を取らないとね。"
  },
  {
    "time": "00:03:40",
    "en": "Perhaps someone with Dylan, Dylan, get in there observing the treatment.",
    "zh": "或許有人和迪倫一起，迪倫，進去觀察治療。",
    "ja": "誰かがディランと一緒に、ディラン、治療を見学して。"
  },
  {
    "time": "00:03:43",
    "en": "She doesn't have anything, does she?",
    "zh": "她沒事吧？",
    "ja": "彼女は何もないよね？"
  },
  {
    "time": "00:03:46",
    "en": "Okay. You got this?",
    "zh": "好，你準備好了嗎？",
    "ja": "はい、準備できた？"
  },
  {
    "time": "00:03:48",
    "en": "Okay. Okay.",
    "zh": "好，好。",
    "ja": "はい、はい。"
  },
  {
    "time": "00:03:50",
    "en": "Move in. There you go. Okay.",
    "zh": "靠近一點。好了。好。",
    "ja": "近づいて。はい、いいよ。"
  },
  {
    "time": "00:03:52",
    "en": "Look at the camera.",
    "zh": "看著相機。",
    "ja": "カメラを見て。"
  },
  {
    "time": "00:03:54",
    "en": "Smile, doctor.",
    "zh": "笑一個，醫生。",
    "ja": "笑って、先生。"
  },
  {
    "time": "00:03:56",
    "en": "Okay, right here. There we go.",
    "zh": "好，就在這裡。好了。",
    "ja": "はい、ここで。いいね。"
  },
  {
    "time": "00:03:58",
    "en": "And...",
    "zh": "然後...",
    "ja": "そして..."
  },
  {
    "time": "00:04:00",
    "en": "If nothing changes, come back and see me tomorrow.",
    "zh": "如果沒變化，明天再來找我。",
    "ja": "何も変わらなければ、明日また来てください。"
  },
  {
    "time": "00:04:04",
    "en": "Okay, and you brassed up.",
    "zh": "好，你握拳了。",
    "ja": "はい、拳を握って。"
  },
  {
    "time": "00:04:06",
    "en": "Knuckles.",
    "zh": "指關節。",
    "ja": "ナックル。"
  },
  {
    "time": "00:04:08",
    "en": "Thank you.",
    "zh": "謝謝你。",
    "ja": "ありがとう。"
  },
  {
    "time": "00:04:09",
    "en": "There you go, Cassie.",
    "zh": "給你，卡西。",
    "ja": "はい、キャシー。"
  },
  {
    "time": "00:04:11",
    "en": "You ready?",
    "zh": "準備好了嗎？",
    "ja": "準備できた？"
  },
  {
    "time": "00:04:12",
    "en": "Last year, the rains damaged the roofing to this clinic and flooded the eastern clinic.",
    "zh": "去年雨水損壞了這家診所的屋頂，還淹了東部的診所。",
    "ja": "去年の雨でこのクリニックの屋根が壊れ、東のクリニックが浸水しました。"
  },
  {
    "time": "00:04:17",
    "en": "It just took out many of our supplies to build locations.",
    "zh": "這摧毀了我們許多建設地點的物資。",
    "ja": "多くの物資が破壊されました。"
  },
  {
    "time": "00:04:20",
    "en": "That's terrible.",
    "zh": "真糟糕。",
    "ja": "ひどいですね。"
  },
  {
    "time": "00:04:22",
    "en": "You're going to take a listen to your lungs.",
    "zh": "我要聽聽你的肺部。",
    "ja": "肺の音を聞きますね。"
  },
  {
    "time": "00:04:25",
    "en": "Take a big breath in.",
    "zh": "深呼吸。",
    "ja": "大きく息を吸って。"
  },
  {
    "time": "00:04:32",
    "en": "Really?",
    "zh": "真的嗎？",
    "ja": "本当？"
  },
  {
    "time": "00:04:34",
    "en": "I'm just going to check this.",
    "zh": "我只是檢查一下這個。",
    "ja": "これをチェックしますね。"
  },
  {
    "time": "00:04:37",
    "en": "Can't you do something about that?",
    "zh": "你不能做點什麼嗎？",
    "ja": "何とかできませんか？"
  },
  {
    "time": "00:04:41",
    "en": "Excuse me.",
    "zh": "不好意思。",
    "ja": "すみません。"
  },
  {
    "time": "00:04:42",
    "en": "Hey.",
    "zh": "嘿。",
    "ja": "ねえ。"
  },
  {
    "time": "00:04:43",
    "en": "You might be more comfortable away from the patients.",
    "zh": "你離病人遠一點可能會比較舒服。",
    "ja": "患者さんから離れた方が楽かもしれません。"
  },
  {
    "time": "00:04:46",
    "en": "I'd be more comfortable if I wasn't here at all.",
    "zh": "如果我根本不在這裡我會更舒服。",
    "ja": "ここにいなければもっと楽です。"
  },
  {
    "time": "00:04:48",
    "en": "Oh.",
    "zh": "喔。",
    "ja": "ああ。"
  },
  {
    "time": "00:04:49",
    "en": "Okay.",
    "zh": "好。",
    "ja": "はい。"
  },
  {
    "time": "00:04:50",
    "en": "These people don't have regular checkups or preventative health care.",
    "zh": "這些人沒有定期檢查或預防醫療。",
    "ja": "この人たちは定期検診や予防医療を受けていません。"
  },
  {
    "time": "00:04:54",
    "en": "Most of our donors want to change that.",
    "zh": "我們大多數捐助者想改變這種情況。",
    "ja": "ほとんどの寄付者はそれを変えたいと思っています。"
  },
  {
    "time": "00:04:56",
    "en": "I'm not most people.",
    "zh": "我不是大多數人。",
    "ja": "私は大多数の人とは違います。"
  },
  {
    "time": "00:04:58",
    "en": "At what point do you just put them down?",
    "zh": "什麼時候你會放棄他們？",
    "ja": "いつ見捨てるんですか？"
  },
  {
    "time": "00:05:02",
    "en": "Oh, I see.",
    "zh": "喔，我懂了。",
    "ja": "ああ、なるほど。"
  },
  {
    "time": "00:05:03",
    "en": "I'm guessing you're just here for the tax right off or maybe a pat on the back from your golf buddies?",
    "zh": "我猜你來這只是為了稅務減免，或是想從高爾夫球友那裡得到拍拍背？",
    "ja": "税控除かゴルフ仲間からの称賛のために来てるんだろう？"
  },
  {
    "time": "00:05:08",
    "en": "I can just as easily take away my donation.",
    "zh": "我也可以輕易撤回我的捐款。",
    "ja": "寄付を取り消すことも簡単にできます。"
  },
  {
    "time": "00:05:11",
    "en": "You did decide to do that.",
    "zh": "你確實決定這麼做了。",
    "ja": "そう決めたんですね。"
  },
  {
    "time": "00:05:12",
    "en": "I wouldn't be surprised.",
    "zh": "我不會感到驚訝。",
    "ja": "驚きませんよ。"
  },
  {
    "time": "00:05:13",
    "en": "You seem pretty heartless.",
    "zh": "你看起來相當無情。",
    "ja": "かなり冷酷に見えますね。"
  },
  {
    "time": "00:05:15",
    "en": "Is that a professional diagnosis?",
    "zh": "那是專業診斷嗎？",
    "ja": "それは専門的な診断ですか？"
  },
  {
    "time": "00:05:17",
    "en": "Yeah.",
    "zh": "是的。",
    "ja": "はい。"
  },
  {
    "time": "00:05:18",
    "en": "I need to treat some of these people you're looking down on if you'll excuse me.",
    "zh": "如果你不介意，我得去治療一些你看不起的人。",
    "ja": "失礼しますが、あなたが見下している人たちを治療しなければなりません。"
  },
  {
    "time": "00:05:22",
    "en": "Blake, we're leaving.",
    "zh": "布雷克，我們走了。",
    "ja": "ブレイク、出発するよ。"
  },
  {
    "time": "00:05:24",
    "en": "Sorry.",
    "zh": "抱歉。",
    "ja": "ごめん。"
  },
  {
    "time": "00:05:25",
    "en": "He has something else scheduled.",
    "zh": "他有其他安排。",
    "ja": "彼は別の予定があります。"
  },
  {
    "time": "00:05:27",
    "en": "Thank you for coming and thank you for the donation.",
    "zh": "謝謝你來，也謝謝你的捐款。",
    "ja": "来てくれてありがとう、寄付も感謝します。"
  },
  {
    "time": "00:05:29",
    "en": "You're welcome.",
    "zh": "不客氣。",
    "ja": "どういたしまして。"
  },
  {
    "time": "00:05:30",
    "en": "Goodbye.",
    "zh": "再見。",
    "ja": "さようなら。"
  },
  {
    "time": "00:05:31",
    "en": "Bye.",
    "zh": "拜。",
    "ja": "バイ。"
  },
  {
    "time": "00:05:32",
    "en": "What did you say to him?",
    "zh": "你跟他說了什麼？",
    "ja": "彼に何を言ったの？"
  },
  {
    "time": "00:05:35",
    "en": "Nothing that wasn't true.",
    "zh": "沒說不實的話。",
    "ja": "真実でないことは言っていません。"
  },
  {
    "time": "00:05:37",
    "en": "Trust me.",
    "zh": "相信我。",
    "ja": "信じて。"
  },
  {
    "time": "00:05:38",
    "en": "With that guy, I think it went as well as it possibly could.",
    "zh": "對那傢伙來說，我想這已經是最好的結果了。",
    "ja": "あの男には、これが最善だったと思う。"
  },
  {
    "time": "00:05:47",
    "en": "Well, that was interesting.",
    "zh": "嗯，那真有趣。",
    "ja": "面白かったね。"
  },
  {
    "time": "00:05:48",
    "en": "You canceled their other donations.",
    "zh": "你取消了他們其他的捐款。",
    "ja": "彼らの他の寄付をキャンセルしたね。"
  },
  {
    "time": "00:05:51",
    "en": "We have two more committed to give them.",
    "zh": "我們還有兩個承諾要給他們。",
    "ja": "あと2件の寄付が約束されています。"
  },
  {
    "time": "00:05:53",
    "en": "This should be grateful I gave them one at all.",
    "zh": "他們應該感激我至少給了他們一筆。",
    "ja": "彼らは少なくとも一つもらったことに感謝すべきだ。"
  },
  {
    "time": "00:05:56",
    "en": "They do.",
    "zh": "他們是的。",
    "ja": "そうだね。"
  },
  {
    "time": "00:05:57",
    "en": "Good work.",
    "zh": "幹得好。",
    "ja": "よくやった。"
  },
  {
    "time": "00:05:58",
    "en": "Someone else can fund them.",
    "zh": "別人可以資助他們。",
    "ja": "他の誰かが資金を出せる。"
  },
  {
    "time": "00:05:59",
    "en": "I'd rather give money to the endangered grasshopper foundation or whatever.",
    "zh": "我寧願把錢給瀕危蚱蜢基金會之類的。",
    "ja": "絶滅危惧種のバッタ基金にでも寄付したい。"
  },
  {
    "time": "00:06:05",
    "en": "Lawrence is supposed to meet with the head of finance.",
    "zh": "勞倫斯應該要和財務主管會面。",
    "ja": "ローレンスは財務責任者と会う予定です。"
  },
  {
    "time": "00:06:08",
    "en": "I want to hear what they found out about the irregularities so far.",
    "zh": "我想知道他們目前發現了什麼不規則情況。",
    "ja": "これまでに不正について何が分かったか聞きたい。"
  },
  {
    "time": "00:06:11",
    "en": "Get us back to the villa right away.",
    "zh": "立刻帶我們回別墅。",
    "ja": "すぐにヴィラに戻ってください。"
  },
  {
    "time": "00:06:13",
    "en": "This traffic right away is going to be another hour.",
    "zh": "這交通馬上還要一小時。",
    "ja": "この渋滞はあと1時間かかります。"
  },
  {
    "time": "00:06:17",
    "en": "We'd be better off pulling over for a bit.",
    "zh": "我們還是暫停一下比較好。",
    "ja": "少し停車した方がいい。"
  },
  {
    "time": "00:06:20",
    "en": "Hey, that's cool.",
    "zh": "嘿，那不錯。",
    "ja": "おお、それいいね。"
  },
  {
    "time": "00:06:21",
    "en": "Hey, Steve, stop the car.",
    "zh": "嘿，史蒂夫，停車。",
    "ja": "ねえ、スティーブ、車止めて。"
  },
  {
    "time": "00:06:23",
    "en": "Pardon?",
    "zh": "什麼？",
    "ja": "え？"
  },
  {
    "time": "00:06:24",
    "en": "Just right here.",
    "zh": "就在這裡。",
    "ja": "ここでいいよ。"
  },
  {
    "time": "00:06:25",
    "en": "What?",
    "zh": "什麼？",
    "ja": "何？"
  },
  {
    "time": "00:06:26",
    "en": "Why?",
    "zh": "為什麼？",
    "ja": "なぜ？"
  },
  {
    "time": "00:06:27",
    "en": "You don't fly this far and not see some sights.",
    "zh": "飛這麼遠不看看風景怎麼行。",
    "ja": "こんな遠くまで来て景色を見ないなんてありえない。"
  }
]